wib/__init__.py
wib/cli.py
wib-0.2.10.dist-info/LICENSE
wib-0.2.10.dist-info/METADATA
wib-0.2.10.dist-info/WHEEL
wib-0.2.10.dist-info/entry_points.txt
wib-0.2.10.dist-info/top_level.txt
wib-0.2.10.dist-info/RECORD
