Metadata-Version: 2.1
Name: wib
Version: 0.2.10
Summary: Simplified common interface to git and hg
Home-page: https://github.com/chengsoonong/wib
Author: Cheng Soon Ong
Author-email: chengsoon.ong@anu.edu.au
License: GPLv3
Platform: any
Classifier: Development Status :: 3 - Alpha
Classifier: Environment :: Console
Classifier: Intended Audience :: Developers
Classifier: Intended Audience :: Science/Research
Classifier: License :: OSI Approved :: GNU General Public License v3 (GPLv3)
Classifier: Operating System :: OS Independent
Classifier: Programming Language :: Python
Classifier: Programming Language :: Python :: 3
Classifier: Topic :: Software Development :: Libraries :: Python Modules
Requires-Dist: click
